large_image_viewer/__init__.py
large_image_viewer/_reader.py
large_image_viewer/_version.py
large_image_viewer/napari.yaml
large_image_viewer/_tests/__init__.py
large_image_viewer/_tests/test_reader.py
Large_Image_Viewer-1.0.0.dist-info/LICENSE
Large_Image_Viewer-1.0.0.dist-info/METADATA
Large_Image_Viewer-1.0.0.dist-info/WHEEL
Large_Image_Viewer-1.0.0.dist-info/entry_points.txt
Large_Image_Viewer-1.0.0.dist-info/top_level.txt
Large_Image_Viewer-1.0.0.dist-info/RECORD
