Metadata-Version: 2.1
Name: Large-Image-Viewer
Version: 1.0.0
Summary: A simple plugin to view large images
Home-page: https://github.com/WyssCenter/Large-Image-Viewer
Author: Nima Mojtahedi
Author-email: nima.mojtahedi@wysscenter.ch
License: MIT
Project-URL: Bug Tracker, https://github.com/WyssCenter/Large-Image-Viewer/issues
Project-URL: Documentation, https://github.com/WyssCenter/Large-Image-Viewer#README.md
Project-URL: Source Code, https://github.com/WyssCenter/Large-Image-Viewer
Project-URL: User Support, https://github.com/WyssCenter/Large-Image-Viewer/issues
Classifier: Development Status :: 3 - Alpha
Classifier: Framework :: napari
Classifier: Intended Audience :: Developers
Classifier: License :: OSI Approved :: MIT License
Classifier: Operating System :: OS Independent
Classifier: Programming Language :: Python
Classifier: Programming Language :: Python :: 3
Classifier: Programming Language :: Python :: 3 :: Only
Classifier: Programming Language :: Python :: 3.8
Classifier: Programming Language :: Python :: 3.9
Classifier: Topic :: Scientific/Engineering :: Image Processing
Requires-Python: >=3.8
License-File: LICENSE
Requires-Dist: numpy
Requires-Dist: dask
Requires-Dist: aicsimageio[base-imageio,czi,dv,lif,nd2]
Requires-Dist: aicspylibczi >=3.1.1
Requires-Dist: fsspec >=2022.8.0
Requires-Dist: readlif >=0.6.4
Requires-Dist: scikit-image
Provides-Extra: testing
Requires-Dist: tox ; extra == 'testing'
Requires-Dist: pytest ; extra == 'testing'
Requires-Dist: pytest-cov ; extra == 'testing'
